cloudagnosticfass-0.0.14-py3.9-nspkg.pth
cloudagnosticfass.py
cloudagnosticfass-0.0.14.dist-info/METADATA
cloudagnosticfass-0.0.14.dist-info/WHEEL
cloudagnosticfass-0.0.14.dist-info/namespace_packages.txt
cloudagnosticfass-0.0.14.dist-info/top_level.txt
cloudagnosticfass-0.0.14.dist-info/RECORD
